elifecrossref/__init__.py
elifecrossref/abstract.py
elifecrossref/access_indicators.py
elifecrossref/body.py
elifecrossref/citation.py
elifecrossref/clinical_trials.py
elifecrossref/collection.py
elifecrossref/component.py
elifecrossref/conf.py
elifecrossref/contributor.py
elifecrossref/crossmark.py
elifecrossref/dataset.py
elifecrossref/dates.py
elifecrossref/doi.py
elifecrossref/elife.py
elifecrossref/funding.py
elifecrossref/generate.py
elifecrossref/head.py
elifecrossref/journal.py
elifecrossref/journal_article.py
elifecrossref/mime_type.py
elifecrossref/peer_review.py
elifecrossref/pending_publication.py
elifecrossref/posted_content.py
elifecrossref/preprint.py
elifecrossref/related.py
elifecrossref/resource_url.py
elifecrossref/status.py
elifecrossref/tags.py
elifecrossref/title.py
elifecrossref/utils.py
elifecrossref/version.py
elifecrossref-0.49.0.dist-info/LICENSE
elifecrossref-0.49.0.dist-info/METADATA
elifecrossref-0.49.0.dist-info/WHEEL
elifecrossref-0.49.0.dist-info/top_level.txt
elifecrossref-0.49.0.dist-info/RECORD
