Metadata-Version: 2.1
Name: elifecrossref
Version: 0.49.0
Summary: eLife Crossref deposit of journal articles.
Home-page: https://github.com/elifesciences/elife-crossref-xml-generation
Maintainer: eLife Sciences Publications Ltd.
Maintainer-email: py@elifesciences.org
License: MIT
Classifier: Development Status :: 3 - Alpha
Classifier: Intended Audience :: Developers
Classifier: License :: OSI Approved :: MIT License
Classifier: Programming Language :: Python :: 3
License-File: LICENSE
Requires-Dist: elifetools >=0.45.0
Requires-Dist: elifearticle >=0.25.0
Requires-Dist: GitPython
Requires-Dist: configparser
Requires-Dist: requests
